ffind/__init__.py
ffind/ffind.py
ffind-1.6.1.dist-info/METADATA
ffind-1.6.1.dist-info/WHEEL
ffind-1.6.1.dist-info/entry_points.txt
ffind-1.6.1.dist-info/licenses/LICENSE.txt
ffind-1.6.1.dist-info/RECORD
