Metadata-Version: 2.4
Name: ffind
Version: 1.6.1
Summary: Sane replacement for command line file search
Project-URL: Homepage, https://github.com/jaimebuelta/ffind
Project-URL: Download, https://github.com/jaimebuelta/ffind/tarball/v1.6.1
Author-email: Jaime Buelta <jaime.buelta@gmail.com>
License-Expression: MIT
License-File: LICENSE.txt
Keywords: file system,searching
Classifier: Programming Language :: Python :: 3
Classifier: Programming Language :: Python :: 3.9
Classifier: Programming Language :: Python :: 3.10
Classifier: Programming Language :: Python :: 3.11
Classifier: Programming Language :: Python :: 3.12
Classifier: Programming Language :: Python :: 3.13
Requires-Python: <4,>=3.9
